simpoly-0.3.5.dist-info/LICENSE
simpoly-0.3.5.dist-info/RECORD
simpoly-0.3.5.dist-info/METADATA
simpoly-0.3.5.dist-info/WHEEL
simpoly-0.3.5.dist-info/top_level.txt
simpoly/__init__.py
simpoly/polygon.pypy310-pp73-x86_64-linux-gnu.so
simpoly/bbox_utils.pypy310-pp73-x86_64-linux-gnu.so
