Metadata-Version: 2.1
Name: simpoly
Version: 0.3.5
Summary: Simple polygon operations
Author-email: ndgnuh <ndgnuh@protonmail.com>
Project-URL: Homepage, https://gitlab.com/ndgnuh/simpoly
Project-URL: Bug Tracker, https://gitlab.com/ndgnuh/simpoly/issues
Classifier: Programming Language :: Python :: 3
Classifier: License :: OSI Approved :: GNU General Public License (GPL)
Classifier: Operating System :: OS Independent
Requires-Python: >=3.7
License-File: LICENSE
